reduct_cli/__init__.py
reduct_cli/__main__.py
reduct_cli/alias.py
reduct_cli/bucket.py
reduct_cli/cli.py
reduct_cli/config.py
reduct_cli/export.py
reduct_cli/mirror.py
reduct_cli/replication.py
reduct_cli/server.py
reduct_cli/token.py
reduct_cli/export_impl/__init__.py
reduct_cli/export_impl/bucket.py
reduct_cli/export_impl/folder.py
reduct_cli/utils/__init__.py
reduct_cli/utils/consoles.py
reduct_cli/utils/error.py
reduct_cli/utils/helpers.py
reduct_cli/utils/humanize.py
reduct_cli-0.10.0.dist-info/LICENSE
reduct_cli-0.10.0.dist-info/METADATA
reduct_cli-0.10.0.dist-info/WHEEL
reduct_cli-0.10.0.dist-info/entry_points.txt
reduct_cli-0.10.0.dist-info/top_level.txt
reduct_cli-0.10.0.dist-info/RECORD
