Metadata-Version: 2.1
Name: reduct-cli
Version: 0.10.0
Summary: CLI client for ReductStore
Author-email: Alexey Timin <atimin@gmail.com>
Maintainer-email: Alexey Timin <atimin@gmail.com>
License: MIT License
Project-URL: ReductStorage, https://www.reduct.store
Project-URL: Documentation, https://cli.reduct.store
Project-URL: SourceCode, https://github.com/reductstore/reduct-cli
Project-URL: Changelog, https://github.com/reductstore/reduct-cli/blob/main/CHANGELOG.md
Project-URL: Twitter, https://twitter.com/ReductStore
Project-URL: Blog, https://www.reductstore/blog
Keywords: cli,reductstore,tool,database,time series database
Classifier: Development Status :: 4 - Beta
Classifier: Programming Language :: Python :: 3 :: Only
Classifier: Environment :: Console
Classifier: Intended Audience :: Information Technology
Classifier: Intended Audience :: Developers
Classifier: Intended Audience :: System Administrators
Classifier: Operating System :: OS Independent
Classifier: Topic :: Database :: Front-Ends
Requires-Python: >=3.9
License-File: LICENSE
Requires-Dist: reduct-py ~=1.8
Requires-Dist: click ~=8.1
Requires-Dist: tomlkit ~=0.12
Requires-Dist: rich ~=13.7
Provides-Extra: docs
Requires-Dist: mkdocs ~=1.5 ; extra == 'docs'
Requires-Dist: mkdocs-material ~=9.5 ; extra == 'docs'
Requires-Dist: plantuml-markdown ~=3.9 ; extra == 'docs'
Requires-Dist: mkdocs-same-dir ~=0.1 ; extra == 'docs'
Requires-Dist: mkdocs-click ~=0.8 ; extra == 'docs'
Provides-Extra: format
Requires-Dist: black ~=23.10 ; extra == 'format'
Provides-Extra: lint
Requires-Dist: pylint ~=3.0 ; extra == 'lint'
Provides-Extra: test
Requires-Dist: pytest ~=7.4 ; extra == 'test'
Requires-Dist: pytest-mock ~=3.12 ; extra == 'test'
Requires-Dist: pytest-asyncio ~=0.23 ; extra == 'test'
